yccdb.py
yccdb-0.5.0.dist-info/METADATA
yccdb-0.5.0.dist-info/WHEEL
yccdb-0.5.0.dist-info/top_level.txt
yccdb-0.5.0.dist-info/RECORD
