Metadata-Version: 2.4
Name: yccdb
Version: 0.5.0
Summary: a db api
Author-email: Th3ou1d3x <Th3ou1d3x@bloodcircuit.org>, Anthony <Anthony@bloodcircuit.org>
License: MIT
Classifier: Programming Language :: Python :: 3
Classifier: License :: OSI Approved :: MIT License
Classifier: Operating System :: OS Independent
Requires-Python: >=3.0
Requires-Dist: requests
